setup.py
django_multiform.egg-info/PKG-INFO
django_multiform.egg-info/SOURCES.txt
django_multiform.egg-info/dependency_links.txt
django_multiform.egg-info/not-zip-safe
django_multiform.egg-info/top_level.txt
multiform/__init__.py
multiform/forms.py