Metadata-Version: 1.1
Name: django-multiform
Version: 0.1
Summary: Wrap several django forms into one form-like object
Home-page: https://github.com/bmispelon/django-multiform/
Author: Baptiste Mispelon <bmispelon@gmail.com>
Author-email: UNKNOWN
License: BSD
Keywords: django,forms,multiform
Platform: UNKNOWN
Classifier: Programming Language :: Python
Classifier: Topic :: Software Development :: Libraries :: Python Modules
Classifier: Framework :: Django
Classifier: Environment :: Web Environment
Classifier: Programming Language :: Python :: 2.6
Classifier: Programming Language :: Python :: 2.7
Classifier: Programming Language :: Python :: 3.2
Classifier: Programming Language :: Python :: 3.3
